{
  "schemaVersion": "2.0.0",
  "docId": "rark.vue.tree",
  "component": {
    "name": "Tree",
    "framework": "vue",
    "package": "@raxium/vue/core",
    "importPath": "@raxium/vue/core",
    "exportName": "Tree",
    "category": "core",
    "description": "用于展示层级结构数据，适合目录浏览、权限节点选择、配置树编辑等场景。基于 Ark UI Tree View 原语构建，支持展开/折叠、单选/多选、复选框勾选、焦点管理以及懒挂载策略。由 Tree、TreeNode、TreeCheckboxNode 组合而成；TreeNode 用于普通选中树，TreeCheckboxNode 用于复选框勾选树；default 插槽内通常递归放置 TreeNode 或 TreeCheckboxNode。",
    "basePrimitive": {
      "library": "@ark-ui/vue/tree-view",
      "primitive": "TreeView.RootProvider",
      "nativeElement": "div"
    },
    "passThrough": {
      "htmlAttributes": [
        "aria-*",
        "data-*"
      ],
      "notes": "透传 Ark UI TreeViewRootBaseProps；theme、ui 为 Rark 扩展。"
    },
    "capabilities": [
      "v-model:expandedValue",
      "v-model:selectedValue",
      "v-model:checkedValue",
      "v-model:focusedValue",
      "theme",
      "ui-override",
      "programmatic-api"
    ],
    "subComponents": ["TreeNode", "TreeCheckboxNode"]
  },
  "contracts": {
    "props": [
      {
        "name": "collection",
        "required": false,
        "requiredSource": "type",
        "typeText": "TreeCollection<T>",
        "typeSchema": { "type": "object" },
        "default": null,
        "defaultKind": "implicit-undefined",
        "nullable": true,
        "passthrough": false,
        "deprecated": false,
        "dependsOn": [],
        "conflictsWith": [],
        "description": "树数据集合（通常由 createTreeCollection 创建）。"
      },
      {
        "name": "selectionMode",
        "required": false,
        "requiredSource": "type",
        "typeText": "'single' | 'multiple'",
        "typeSchema": { "enum": ["single", "multiple"] },
        "default": null,
        "defaultKind": "implicit-undefined",
        "nullable": true,
        "passthrough": false,
        "deprecated": false,
        "dependsOn": [],
        "conflictsWith": [],
        "description": "选中模式，影响 selectedValue 语义。"
      },
      {
        "name": "expandedValue",
        "required": false,
        "requiredSource": "type",
        "typeText": "TreeValueType[]",
        "typeSchema": { "type": "array" },
        "default": null,
        "defaultKind": "implicit-undefined",
        "nullable": true,
        "passthrough": false,
        "deprecated": false,
        "dependsOn": [],
        "conflictsWith": [],
        "description": "受控展开值。"
      },
      {
        "name": "defaultExpandedValue",
        "required": false,
        "requiredSource": "type",
        "typeText": "TreeValueType[]",
        "typeSchema": { "type": "array" },
        "default": null,
        "defaultKind": "implicit-undefined",
        "nullable": true,
        "passthrough": false,
        "deprecated": false,
        "dependsOn": [],
        "conflictsWith": [],
        "description": "非受控初始展开值。"
      },
      {
        "name": "selectedValue",
        "required": false,
        "requiredSource": "type",
        "typeText": "TreeValueType[]",
        "typeSchema": { "type": "array" },
        "default": null,
        "defaultKind": "implicit-undefined",
        "nullable": true,
        "passthrough": false,
        "deprecated": false,
        "dependsOn": [],
        "conflictsWith": [],
        "description": "受控选中值。"
      },
      {
        "name": "defaultSelectedValue",
        "required": false,
        "requiredSource": "type",
        "typeText": "TreeValueType[]",
        "typeSchema": { "type": "array" },
        "default": null,
        "defaultKind": "implicit-undefined",
        "nullable": true,
        "passthrough": false,
        "deprecated": false,
        "dependsOn": [],
        "conflictsWith": [],
        "description": "非受控初始选中值。"
      },
      {
        "name": "checkedValue",
        "required": false,
        "requiredSource": "type",
        "typeText": "TreeValueType[]",
        "typeSchema": { "type": "array" },
        "default": null,
        "defaultKind": "implicit-undefined",
        "nullable": true,
        "passthrough": false,
        "deprecated": false,
        "dependsOn": [],
        "conflictsWith": [],
        "description": "复选框树受控勾选值。"
      },
      {
        "name": "defaultCheckedValue",
        "required": false,
        "requiredSource": "type",
        "typeText": "TreeValueType[]",
        "typeSchema": { "type": "array" },
        "default": null,
        "defaultKind": "implicit-undefined",
        "nullable": true,
        "passthrough": false,
        "deprecated": false,
        "dependsOn": [],
        "conflictsWith": [],
        "description": "非受控初始勾选值。"
      },
      {
        "name": "focusedValue",
        "required": false,
        "requiredSource": "type",
        "typeText": "TreeValueType",
        "typeSchema": { "oneOf": [{ "type": "string" }, { "type": "number" }, { "type": "boolean" }, { "type": "null" }] },
        "default": null,
        "defaultKind": "implicit-undefined",
        "nullable": true,
        "passthrough": false,
        "deprecated": false,
        "dependsOn": [],
        "conflictsWith": [],
        "description": "当前焦点节点值。"
      },
      {
        "name": "defaultFocusedValue",
        "required": false,
        "requiredSource": "type",
        "typeText": "TreeValueType",
        "typeSchema": { "oneOf": [{ "type": "string" }, { "type": "number" }, { "type": "boolean" }, { "type": "null" }] },
        "default": null,
        "defaultKind": "implicit-undefined",
        "nullable": true,
        "passthrough": false,
        "deprecated": false,
        "dependsOn": [],
        "conflictsWith": [],
        "description": "非受控初始焦点值。"
      },
      {
        "name": "lazyMount",
        "required": false,
        "requiredSource": "type",
        "typeText": "boolean",
        "typeSchema": { "type": "boolean" },
        "default": null,
        "defaultKind": "implicit-undefined",
        "nullable": true,
        "passthrough": true,
        "deprecated": false,
        "dependsOn": [],
        "conflictsWith": [],
        "description": "懒挂载：仅当节点展开时挂载子节点 DOM（示例见 LargeData）。"
      },
      {
        "name": "unmountOnExit",
        "required": false,
        "requiredSource": "type",
        "typeText": "boolean",
        "typeSchema": { "type": "boolean" },
        "default": null,
        "defaultKind": "implicit-undefined",
        "nullable": true,
        "passthrough": true,
        "deprecated": false,
        "dependsOn": [],
        "conflictsWith": [],
        "description": "退出卸载：折叠时卸载子节点 DOM，降低非激活分支开销（示例见 LargeData）。"
      },
      {
        "name": "class",
        "required": false,
        "requiredSource": "type",
        "typeText": "string | array | object",
        "typeSchema": {
          "anyOf": [{ "type": "string" }, { "type": "array" }, { "type": "object" }]
        },
        "default": null,
        "defaultKind": "implicit-undefined",
        "nullable": true,
        "passthrough": false,
        "deprecated": false,
        "dependsOn": [],
        "conflictsWith": [],
        "description": "根节点附加 class。"
      },
      {
        "name": "theme",
        "required": false,
        "requiredSource": "type",
        "typeText": "ThemeCrafts<'tvTree'>",
        "typeSchema": { "type": "object" },
        "default": null,
        "defaultKind": "implicit-undefined",
        "nullable": true,
        "passthrough": false,
        "deprecated": false,
        "dependsOn": [],
        "conflictsWith": [],
        "description": "主题参数与 crafts 覆盖入口。"
      },
      {
        "name": "ui",
        "required": false,
        "requiredSource": "type",
        "typeText": "{ root?: class; tree?: class }",
        "typeSchema": {
          "type": "object",
          "properties": { "root": {}, "tree": {} }
        },
        "default": null,
        "defaultKind": "implicit-undefined",
        "nullable": true,
        "passthrough": false,
        "deprecated": false,
        "dependsOn": [],
        "conflictsWith": [],
        "description": "根与树容器 class 覆盖。"
      }
    ],
    "events": [
      {
        "name": "update:expandedValue",
        "payload": { "typeText": "(value: TreeValueType[])", "typeSchema": { "type": "object" } },
        "emitWhen": [{ "expr": "expanded_changed", "kind": "runtime-hook" }],
        "notEmitWhen": [],
        "order": ["emit:update:expandedValue"],
        "description": "展开值受控同步。"
      },
      {
        "name": "update:selectedValue",
        "payload": { "typeText": "(value: TreeValueType[])", "typeSchema": { "type": "object" } },
        "emitWhen": [{ "expr": "selection_changed", "kind": "runtime-hook" }],
        "notEmitWhen": [],
        "order": ["emit:update:selectedValue"],
        "description": "选中值受控同步。"
      },
      {
        "name": "update:checkedValue",
        "payload": { "typeText": "(value: TreeValueType[])", "typeSchema": { "type": "object" } },
        "emitWhen": [{ "expr": "checked_changed", "kind": "runtime-hook" }],
        "notEmitWhen": [],
        "order": ["emit:update:checkedValue"],
        "description": "勾选值受控同步。"
      },
      {
        "name": "update:focusedValue",
        "payload": { "typeText": "(value: TreeValueType)", "typeSchema": { "type": "object" } },
        "emitWhen": [{ "expr": "focus_changed", "kind": "runtime-hook" }],
        "notEmitWhen": [],
        "order": ["emit:update:focusedValue"],
        "description": "焦点值受控同步。"
      },
      {
        "name": "expandedChange",
        "payload": { "typeText": "(details: ExpandedChangeDetails)", "typeSchema": { "type": "object" } },
        "emitWhen": [{ "expr": "expanded_changed", "kind": "runtime-hook" }],
        "notEmitWhen": [],
        "order": ["emit:expandedChange"],
        "description": "展开状态变化时触发。"
      },
      {
        "name": "selectionChange",
        "payload": { "typeText": "(details: SelectionChangeDetails)", "typeSchema": { "type": "object" } },
        "emitWhen": [{ "expr": "selection_changed", "kind": "runtime-hook" }],
        "notEmitWhen": [],
        "order": ["emit:selectionChange"],
        "description": "选中状态变化时触发。"
      },
      {
        "name": "checkedChange",
        "payload": { "typeText": "(details: CheckedChangeDetails)", "typeSchema": { "type": "object" } },
        "emitWhen": [{ "expr": "checked_changed", "kind": "runtime-hook" }],
        "notEmitWhen": [],
        "order": ["emit:checkedChange"],
        "description": "勾选状态变化时触发。"
      },
      {
        "name": "focusChange",
        "payload": { "typeText": "(details: FocusChangeDetails)", "typeSchema": { "type": "object" } },
        "emitWhen": [{ "expr": "focus_changed", "kind": "runtime-hook" }],
        "notEmitWhen": [],
        "order": ["emit:focusChange"],
        "description": "焦点变化时触发。"
      }
    ],
    "slots": [
      {
        "name": "default",
        "slotPropsSchema": { "type": "object", "properties": {}, "additionalProperties": false },
        "renderWhen": [{ "expr": "always" }],
        "fallback": null,
        "description": "树节点内容（通常放置递归 TreeNode 或 TreeCheckboxNode）。"
      },
      {
        "name": "prefix",
        "slotPropsSchema": { "type": "object", "properties": {}, "additionalProperties": false },
        "renderWhen": [{ "expr": "always" }],
        "fallback": null,
        "description": "树容器前置附加区域。"
      },
      {
        "name": "suffix",
        "slotPropsSchema": { "type": "object", "properties": {}, "additionalProperties": false },
        "renderWhen": [{ "expr": "always" }],
        "fallback": null,
        "description": "树容器后置附加区域。"
      }
    ],
    "themeConfiguration": {
      "fields": [
        {
          "name": "size",
          "typeText": "'xs' | 'sm' | 'base' | 'lg'",
          "typeSchema": { "enum": ["xs", "sm", "base", "lg"] },
          "default": "base",
          "defaultKind": "explicit-doc",
          "description": "节点行高、文本和图标尺寸节奏。"
        },
        {
          "name": "crafts",
          "typeText": "object",
          "typeSchema": { "type": "object" },
          "default": null,
          "defaultKind": "unknown",
          "description": "覆盖 tvTree 及关联 crafts（branch/item/checkbox）。"
        }
      ]
    },
    "uiConfiguration": {
      "fields": [
        { "name": "ui.root", "typeText": "string | array | object", "typeSchema": { "anyOf": [{ "type": "string" }, { "type": "array" }, { "type": "object" }] }, "default": null, "defaultKind": "implicit-undefined", "description": "根容器 class 覆盖" },
        { "name": "ui.tree", "typeText": "string | array | object", "typeSchema": { "anyOf": [{ "type": "string" }, { "type": "array" }, { "type": "object" }] }, "default": null, "defaultKind": "implicit-undefined", "description": "树容器 class 覆盖" }
      ]
    }
  },
  "subComponents": {
    "TreeNode": {
      "props": [
        {
          "name": "node",
          "required": true,
          "requiredSource": "runtime",
          "typeText": "TreeNodeData",
          "typeSchema": { "type": "object" },
          "default": null,
          "defaultKind": "implicit-undefined",
          "nullable": false,
          "passthrough": false,
          "deprecated": false,
          "dependsOn": [],
          "conflictsWith": [],
          "description": "当前节点数据（必填）。"
        },
        {
          "name": "indexPath",
          "required": true,
          "requiredSource": "runtime",
          "typeText": "number[]",
          "typeSchema": { "type": "array", "items": { "type": "number" } },
          "default": [],
          "defaultKind": "explicit-runtime",
          "nullable": false,
          "passthrough": false,
          "deprecated": false,
          "dependsOn": [],
          "conflictsWith": [],
          "description": "当前节点路径索引（必填）。"
        },
        {
          "name": "keyMap",
          "required": false,
          "requiredSource": "type",
          "typeText": "Partial<TreeKeyMap>",
          "typeSchema": {
            "type": "object",
            "properties": {
              "id": { "type": "string" },
              "name": { "type": "string" },
              "children": { "type": "string" },
              "icon": { "type": "string" }
            }
          },
          "default": { "id": "id", "name": "name", "children": "children", "icon": "icon" },
          "defaultKind": "explicit-runtime",
          "nullable": false,
          "passthrough": false,
          "deprecated": false,
          "dependsOn": [],
          "conflictsWith": [],
          "description": "将默认字段映射到自定义数据结构（示例见 CustomDatatype）。"
        },
        {
          "name": "nodeIndent",
          "required": false,
          "requiredSource": "type",
          "typeText": "number",
          "typeSchema": { "type": "number" },
          "default": null,
          "defaultKind": "implicit-undefined",
          "nullable": true,
          "passthrough": false,
          "deprecated": false,
          "dependsOn": [],
          "conflictsWith": [],
          "description": "节点缩进值（px）。"
        },
        {
          "name": "renderIcon",
          "required": false,
          "requiredSource": "type",
          "typeText": "(props: RenderIconProps) => VNode",
          "typeSchema": { "type": "function" },
          "default": null,
          "defaultKind": "explicit-runtime",
          "nullable": false,
          "passthrough": false,
          "deprecated": false,
          "dependsOn": [],
          "conflictsWith": [],
          "description": "自定义图标渲染函数（示例见 CustomPropsRender）。"
        },
        {
          "name": "renderName",
          "required": false,
          "requiredSource": "type",
          "typeText": "(props: RenderNameProps) => VNode | string",
          "typeSchema": { "type": "function" },
          "default": null,
          "defaultKind": "explicit-runtime",
          "nullable": false,
          "passthrough": false,
          "deprecated": false,
          "dependsOn": [],
          "conflictsWith": [],
          "description": "自定义名称渲染函数。"
        },
        {
          "name": "ui",
          "required": false,
          "requiredSource": "type",
          "typeText": "object",
          "typeSchema": {
            "type": "object",
            "properties": {
              "branch": {},
              "branchControl": {},
              "branchTitle": {},
              "branchIcon": {},
              "branchText": {},
              "branchIndicator": {},
              "branchContent": {},
              "branchIndentGuide": {},
              "item": {},
              "itemTitle": {},
              "itemIcon": {},
              "itemText": {}
            }
          },
          "default": {},
          "defaultKind": "explicit-runtime",
          "nullable": false,
          "passthrough": false,
          "deprecated": false,
          "dependsOn": [],
          "conflictsWith": [],
          "description": "分支/叶子各结构节点 class 覆盖（branch、branchControl、branchTitle、branchIcon、branchText、branchIndicator、branchContent、branchIndentGuide、item、itemTitle、itemIcon、itemText）。"
        }
      ],
      "slots": [
        {
          "name": "branch",
          "slotPropsSchema": {
            "type": "object",
            "properties": {
              "node": { "type": "object" },
              "keyMap": { "type": "object" },
              "state": { "type": "object" }
            },
            "additionalProperties": false
          },
          "renderWhen": [{ "expr": "node 有 children" }],
          "fallback": null,
          "description": "分支节点自定义渲染。"
        },
        {
          "name": "item",
          "slotPropsSchema": {
            "type": "object",
            "properties": {
              "node": { "type": "object" },
              "keyMap": { "type": "object" },
              "state": { "type": "object" }
            },
            "additionalProperties": false
          },
          "renderWhen": [{ "expr": "node 无 children" }],
          "fallback": null,
          "description": "叶子节点自定义渲染。"
        }
      ],
      "events": [],
      "themeConfiguration": { "fields": [] },
      "uiConfiguration": {
        "fields": [
          { "name": "ui.branch*", "typeText": "HTMLAttributes['class']", "typeSchema": { "anyOf": [{ "type": "string" }, { "type": "array" }, { "type": "object" }] }, "default": null, "defaultKind": "implicit-undefined", "description": "分支节点结构样式覆盖（branch、branchControl、branchTitle、branchIcon、branchText、branchIndicator、branchContent、branchIndentGuide）" },
          { "name": "ui.item*", "typeText": "HTMLAttributes['class']", "typeSchema": { "anyOf": [{ "type": "string" }, { "type": "array" }, { "type": "object" }] }, "default": null, "defaultKind": "implicit-undefined", "description": "叶子节点结构样式覆盖（item、itemTitle、itemIcon、itemText）" }
        ]
      }
    },
    "TreeCheckboxNode": {
      "props": [
        {
          "name": "node",
          "required": true,
          "requiredSource": "runtime",
          "typeText": "TreeNodeData",
          "typeSchema": { "type": "object" },
          "default": null,
          "defaultKind": "implicit-undefined",
          "nullable": false,
          "passthrough": false,
          "deprecated": false,
          "dependsOn": [],
          "conflictsWith": [],
          "description": "同 TreeNode。"
        },
        {
          "name": "indexPath",
          "required": true,
          "requiredSource": "runtime",
          "typeText": "number[]",
          "typeSchema": { "type": "array", "items": { "type": "number" } },
          "default": [],
          "defaultKind": "explicit-runtime",
          "nullable": false,
          "passthrough": false,
          "deprecated": false,
          "dependsOn": [],
          "conflictsWith": [],
          "description": "同 TreeNode。"
        },
        {
          "name": "keyMap",
          "required": false,
          "requiredSource": "type",
          "typeText": "Partial<TreeKeyMap>",
          "typeSchema": {
            "type": "object",
            "properties": {
              "id": { "type": "string" },
              "name": { "type": "string" },
              "children": { "type": "string" },
              "icon": { "type": "string" }
            }
          },
          "default": { "id": "id", "name": "name", "children": "children", "icon": "icon" },
          "defaultKind": "explicit-runtime",
          "nullable": false,
          "passthrough": false,
          "deprecated": false,
          "dependsOn": [],
          "conflictsWith": [],
          "description": "同 TreeNode。"
        },
        {
          "name": "nodeIndent",
          "required": false,
          "requiredSource": "type",
          "typeText": "number",
          "typeSchema": { "type": "number" },
          "default": null,
          "defaultKind": "implicit-undefined",
          "nullable": true,
          "passthrough": false,
          "deprecated": false,
          "dependsOn": [],
          "conflictsWith": [],
          "description": "同 TreeNode。"
        },
        {
          "name": "renderIcon",
          "required": false,
          "requiredSource": "type",
          "typeText": "(props: RenderIconProps) => VNode",
          "typeSchema": { "type": "function" },
          "default": null,
          "defaultKind": "explicit-runtime",
          "nullable": false,
          "passthrough": false,
          "deprecated": false,
          "dependsOn": [],
          "conflictsWith": [],
          "description": "同 TreeNode。"
        },
        {
          "name": "renderName",
          "required": false,
          "requiredSource": "type",
          "typeText": "(props: RenderNameProps) => VNode | string",
          "typeSchema": { "type": "function" },
          "default": null,
          "defaultKind": "explicit-runtime",
          "nullable": false,
          "passthrough": false,
          "deprecated": false,
          "dependsOn": [],
          "conflictsWith": [],
          "description": "同 TreeNode。"
        },
        {
          "name": "ui",
          "required": false,
          "requiredSource": "type",
          "typeText": "object",
          "typeSchema": {
            "type": "object",
            "properties": {
              "branch": {},
              "branchControl": {},
              "branchTitle": {},
              "branchIcon": {},
              "branchText": {},
              "branchIndicator": {},
              "branchContent": {},
              "branchIndentGuide": {},
              "branchCheckbox": {},
              "branchCheckboxIndicator": {},
              "item": {},
              "itemTitle": {},
              "itemIcon": {},
              "itemText": {},
              "itemCheckbox": {},
              "itemCheckboxIndicator": {}
            }
          },
          "default": {},
          "defaultKind": "explicit-runtime",
          "nullable": false,
          "passthrough": false,
          "deprecated": false,
          "dependsOn": [],
          "conflictsWith": [],
          "description": "除 TreeNode.ui 字段外，还有 branchCheckbox、branchCheckboxIndicator、itemCheckbox、itemCheckboxIndicator。"
        }
      ],
      "slots": [
        {
          "name": "branch",
          "slotPropsSchema": {
            "type": "object",
            "properties": {
              "node": { "type": "object" },
              "keyMap": { "type": "object" },
              "state": { "type": "object" }
            },
            "additionalProperties": false
          },
          "renderWhen": [{ "expr": "node 有 children" }],
          "fallback": null,
          "description": "同 TreeNode.branch，并附带复选框渲染语义。"
        },
        {
          "name": "item",
          "slotPropsSchema": {
            "type": "object",
            "properties": {
              "node": { "type": "object" },
              "keyMap": { "type": "object" },
              "state": { "type": "object" }
            },
            "additionalProperties": false
          },
          "renderWhen": [{ "expr": "node 无 children" }],
          "fallback": null,
          "description": "同 TreeNode.item，并附带复选框渲染语义。"
        }
      ],
      "events": [],
      "themeConfiguration": { "fields": [] },
      "uiConfiguration": {
        "fields": [
          { "name": "ui.branch*", "typeText": "HTMLAttributes['class']", "typeSchema": { "anyOf": [{ "type": "string" }, { "type": "array" }, { "type": "object" }] }, "default": null, "defaultKind": "implicit-undefined", "description": "分支节点结构样式覆盖" },
          { "name": "ui.item*", "typeText": "HTMLAttributes['class']", "typeSchema": { "anyOf": [{ "type": "string" }, { "type": "array" }, { "type": "object" }] }, "default": null, "defaultKind": "implicit-undefined", "description": "叶子节点结构样式覆盖" },
          { "name": "ui.branchCheckbox*", "typeText": "HTMLAttributes['class']", "typeSchema": { "anyOf": [{ "type": "string" }, { "type": "array" }, { "type": "object" }] }, "default": null, "defaultKind": "implicit-undefined", "description": "分支节点复选框控制区与指示器样式覆盖（branchCheckbox、branchCheckboxIndicator）" },
          { "name": "ui.itemCheckbox*", "typeText": "HTMLAttributes['class']", "typeSchema": { "anyOf": [{ "type": "string" }, { "type": "array" }, { "type": "object" }] }, "default": null, "defaultKind": "implicit-undefined", "description": "叶子节点复选框控制区与指示器样式覆盖（itemCheckbox、itemCheckboxIndicator）" }
        ]
      }
    }
  },
  "behaviorModel": {
    "stateVars": {
      "expandedValue": "TreeValueType[]",
      "selectedValue": "TreeValueType[]",
      "checkedValue": "TreeValueType[]",
      "focusedValue": "TreeValueType|null"
    },
    "derived": {
      "expandedSet": "Set(expandedValue)",
      "selectedSet": "Set(selectedValue)"
    },
    "transitions": [
      {
        "on": "toggleExpand",
        "guard": "node 存在",
        "effects": ["更新 expandedValue", "emit(expandedChange)"]
      },
      {
        "on": "select",
        "guard": "!disabled",
        "effects": ["更新 selectedValue", "emit(selectionChange)"]
      },
      {
        "on": "check",
        "guard": "!disabled",
        "effects": ["更新 checkedValue", "emit(checkedChange)"]
      }
    ]
  },
  "examples": [
    { "id": "basic", "mcp": { "server": "raxium", "tool": "get-example", "args": { "framework": "vue", "componentName": "Tree" }, "exampleId": "basic" }, "description": "基础树（展开/折叠 + 选中）" },
    { "id": "selection-modes", "mcp": { "server": "raxium", "tool": "get-example", "args": { "framework": "vue", "componentName": "Tree" }, "exampleId": "selection-modes" }, "description": "选中模式（单选 / 多选）" },
    { "id": "disabled-nodes", "mcp": { "server": "raxium", "tool": "get-example", "args": { "framework": "vue", "componentName": "Tree" }, "exampleId": "disabled-nodes" }, "description": "禁用节点" },
    { "id": "checkbox", "mcp": { "server": "raxium", "tool": "get-example", "args": { "framework": "vue", "componentName": "Tree" }, "exampleId": "checkbox" }, "description": "复选框树（checkedValue）" },
    { "id": "large-data", "mcp": { "server": "raxium", "tool": "get-example", "args": { "framework": "vue", "componentName": "Tree" }, "exampleId": "large-data" }, "description": "懒挂载与大数据" },
    { "id": "custom-render", "mcp": { "server": "raxium", "tool": "get-example", "args": { "framework": "vue", "componentName": "Tree" }, "exampleId": "custom-render" }, "description": "自定义节点渲染" },
    { "id": "custom-props-render", "mcp": { "server": "raxium", "tool": "get-example", "args": { "framework": "vue", "componentName": "Tree" }, "exampleId": "custom-props-render" }, "description": "通过 props 自定义渲染函数" },
    { "id": "custom-datatype", "mcp": { "server": "raxium", "tool": "get-example", "args": { "framework": "vue", "componentName": "Tree" }, "exampleId": "custom-datatype" }, "description": "自定义数据结构" },
    { "id": "events", "mcp": { "server": "raxium", "tool": "get-example", "args": { "framework": "vue", "componentName": "Tree" }, "exampleId": "events" }, "description": "事件监听" },
    { "id": "sizes", "mcp": { "server": "raxium", "tool": "get-example", "args": { "framework": "vue", "componentName": "Tree" }, "exampleId": "sizes" }, "description": "尺寸变体" }
  ],
  "generationHints": {
    "preferredUsageOrder": ["collection", "selectionMode", "expandedValue/selectedValue/checkedValue", "theme"],
    "safeDefaults": {},
    "a11yChecklist": [
      "建议为节点文本提供稳定可读标签",
      "禁用节点通过 isNodeDisabled/数据字段统一声明",
      "大数据场景搭配 lazyMount/unmountOnExit"
    ],
    "codegenTemplates": {
      "minimal": "<Tree :collection=\"collection\"><TreeNode v-for=\"...\" :node=\"node\" :index-path=\"path\" /></Tree>",
      "checkbox": "<Tree v-model:checked-value=\"checked\" :collection=\"collection\"><TreeCheckboxNode v-for=\"(node, index) in rootNode.children\" :key=\"node.id\" :node=\"node\" :index-path=\"[index]\" /></Tree>",
      "customDatatype": "<Tree :collection=\"collection\"><TreeNode :node=\"node\" :index-path=\"path\" :key-map=\"{ id:'key', name:'label', children:'items' }\" /></Tree>"
    },
    "antiPatterns": [
      "在 TreeNode/TreeCheckboxNode 中自定义数据结构时未配置 keyMap，导致字段映射错误",
      "在视图层重复解析结构而非用 createTreeCollection 收敛"
    ]
  },
  "provenance": {
    "sources": [
      { "path": "./tree.doc.mdx", "kind": "doc" },
      { "path": "./props.ts", "kind": "type" },
      { "path": "./Tree.vue", "kind": "runtime" },
      { "path": "./TreeNode.tsx", "kind": "runtime" },
      { "path": "./TreeCheckboxNode.tsx", "kind": "runtime" },
      { "path": "./tree.d.ts", "kind": "type" },
      { "path": "./tree.stories.ts", "kind": "story" }
    ],
    "precedence": ["runtime", "type", "doc"],
    "fieldSourceMap": {
      "contracts.themeConfiguration.fields.size.default": "doc",
      "contracts.props.lazyMount": "doc",
      "contracts.props.unmountOnExit": "doc"
    }
  }
}
